simbricks/schemas/__init__.py
simbricks/schemas/base.py
simbricks_schemas-0.3.6.dist-info/METADATA
simbricks_schemas-0.3.6.dist-info/WHEEL
simbricks_schemas-0.3.6.dist-info/RECORD
